gull_api/__init__.py
gull_api/config.py
gull_api/db.py
gull_api/main.py
gull_api/run_gull_api.py
gull_api-0.0.15.dist-info/LICENSE
gull_api-0.0.15.dist-info/METADATA
gull_api-0.0.15.dist-info/WHEEL
gull_api-0.0.15.dist-info/entry_points.txt
gull_api-0.0.15.dist-info/RECORD
