Metadata-Version: 2.1
Name: gull-api
Version: 0.0.15
Summary: A REST API for running Large Language Models
Home-page: https://github.com/mdbecker/gull_api
License: MIT
Keywords: api,artificial-intelligence,automation,bot,deep-learning,fastapi,GPT,language-models,large-language-models,machine-learning,microservices,natural-language-processing,NLP,openai,REST,text,text-generation,web-api
Author: Michael Becker
Author-email: mdbecker@gmail.com
Requires-Python: >=3.10,<4.0
Classifier: Development Status :: 3 - Alpha
Classifier: Environment :: Web Environment
Classifier: Framework :: FastAPI
Classifier: Intended Audience :: Developers
Classifier: Intended Audience :: Science/Research
Classifier: License :: OSI Approved :: MIT License
Classifier: License :: Other/Proprietary License
Classifier: Natural Language :: English
Classifier: Operating System :: OS Independent
Classifier: Programming Language :: Python
Classifier: Programming Language :: Python :: 3
Classifier: Programming Language :: Python :: 3.10
Classifier: Programming Language :: Python :: 3.11
Classifier: Topic :: Internet :: WWW/HTTP :: WSGI :: Application
Classifier: Topic :: Scientific/Engineering :: Artificial Intelligence
Classifier: Topic :: Text Processing
Requires-Dist: SQLAlchemy (>=2.0.16,<3.0.0)
Requires-Dist: fastapi (>=0.97.0,<0.98.0)
Requires-Dist: pydantic (>=1.10.9,<2.0.0)
Requires-Dist: python-dotenv (>=1.0.0,<2.0.0)
Requires-Dist: uvicorn (>=0.22.0,<0.23.0)
Project-URL: Documentation, https://github.com/mdbecker/gull_api/blob/main/README.md
Project-URL: Repository, https://github.com/mdbecker/gull_api
